PyHP3478A/HP3478A.py
PyHP3478A/__init__.py
PyHP3478A-0.5.dist-info/LICENSE
PyHP3478A-0.5.dist-info/METADATA
PyHP3478A-0.5.dist-info/WHEEL
PyHP3478A-0.5.dist-info/top_level.txt
PyHP3478A-0.5.dist-info/RECORD
