Metadata-Version: 2.1
Name: PyHP3478A
Version: 0.5
Summary: HP3478A python interface
Home-page: https://github.com/Minu-IU3IRR/PyHP3478A
Author: Manuel Minutello
License: MIT
License-File: LICENSE
Requires-Dist: PyAR488
